<?xml version="1.0" encoding="utf-8"?>
<TextureAtlas imagePath="dreamslug.png">
	<!-- Created with Adobe Animate version 24.0.7.61 -->
	<!-- http://www.adobe.com/products/animate.html -->
	<SubTexture name="slugcatdown0000" x="16" y="16" width="298" height="412"/>
	<SubTexture name="slugcatdown0001" x="16" y="16" width="298" height="412"/>
	<SubTexture name="slugcatdown0002" x="330" y="16" width="298" height="412"/>
	<SubTexture name="slugcatdown0003" x="330" y="16" width="298" height="412"/>
	<SubTexture name="slugcatdown0004" x="644" y="16" width="298" height="412"/>
	<SubTexture name="slugcatdown0005" x="644" y="16" width="298" height="412"/>
	<SubTexture name="slugcatdown0006" x="644" y="16" width="298" height="412"/>
	<SubTexture name="slugcatdown0007" x="644" y="16" width="298" height="412"/>
	<SubTexture name="slugcatdown0008" x="644" y="16" width="298" height="412"/>
	<SubTexture name="slugcatdown0009" x="644" y="16" width="298" height="412"/>
	<SubTexture name="slugcatdown0010" x="644" y="16" width="298" height="412"/>
	<SubTexture name="slugcatdown0011" x="644" y="16" width="298" height="412"/>
	<SubTexture name="slugcatdown0012" x="644" y="16" width="298" height="412"/>
	<SubTexture name="slugcatdown0013" x="644" y="16" width="298" height="412"/>
	<SubTexture name="slugcatdown0014" x="644" y="16" width="298" height="412"/>
	<SubTexture name="slugcatidle0000" x="958" y="16" width="274" height="446"/>
	<SubTexture name="slugcatidle0001" x="958" y="16" width="274" height="446"/>
	<SubTexture name="slugcatidle0002" x="1248" y="16" width="274" height="446"/>
	<SubTexture name="slugcatidle0003" x="1248" y="16" width="274" height="446"/>
	<SubTexture name="slugcatidle0004" x="1538" y="16" width="274" height="446"/>
	<SubTexture name="slugcatidle0005" x="1538" y="16" width="274" height="446"/>
	<SubTexture name="slugcatidle0006" x="16" y="478" width="274" height="446"/>
	<SubTexture name="slugcatidle0007" x="16" y="478" width="274" height="446"/>
	<SubTexture name="slugcatidle0008" x="306" y="478" width="274" height="446"/>
	<SubTexture name="slugcatidle0009" x="306" y="478" width="274" height="446"/>
	<SubTexture name="slugcatidle0010" x="596" y="478" width="274" height="446"/>
	<SubTexture name="slugcatidle0011" x="596" y="478" width="274" height="446"/>
	<SubTexture name="slugcatidle0012" x="1538" y="16" width="274" height="446"/>
	<SubTexture name="slugcatidle0013" x="1538" y="16" width="274" height="446"/>
	<SubTexture name="slugcatidle0014" x="886" y="478" width="274" height="446"/>
	<SubTexture name="slugcatidle0015" x="886" y="478" width="274" height="446"/>
	<SubTexture name="slugcatidle0016" x="958" y="16" width="274" height="446"/>
	<SubTexture name="slugcatidle0017" x="958" y="16" width="274" height="446"/>
	<SubTexture name="slugcatleft0000" x="1176" y="478" width="309" height="460"/>
	<SubTexture name="slugcatleft0001" x="1176" y="478" width="309" height="460"/>
	<SubTexture name="slugcatleft0002" x="1501" y="478" width="309" height="460"/>
	<SubTexture name="slugcatleft0003" x="1501" y="478" width="309" height="460"/>
	<SubTexture name="slugcatleft0004" x="16" y="954" width="309" height="460"/>
	<SubTexture name="slugcatleft0005" x="16" y="954" width="309" height="460"/>
	<SubTexture name="slugcatleft0006" x="16" y="954" width="309" height="460"/>
	<SubTexture name="slugcatleft0007" x="16" y="954" width="309" height="460"/>
	<SubTexture name="slugcatleft0008" x="16" y="954" width="309" height="460"/>
	<SubTexture name="slugcatleft0009" x="16" y="954" width="309" height="460"/>
	<SubTexture name="slugcatleft0010" x="16" y="954" width="309" height="460"/>
	<SubTexture name="slugcatleft0011" x="16" y="954" width="309" height="460"/>
	<SubTexture name="slugcatleft0012" x="16" y="954" width="309" height="460"/>
	<SubTexture name="slugcatleft0013" x="16" y="954" width="309" height="460"/>
	<SubTexture name="slugcatleft0014" x="16" y="954" width="309" height="460"/>
	<SubTexture name="slugcatright0000" x="341" y="954" width="279" height="447"/>
	<SubTexture name="slugcatright0001" x="341" y="954" width="279" height="447"/>
	<SubTexture name="slugcatright0002" x="636" y="954" width="279" height="447"/>
	<SubTexture name="slugcatright0003" x="636" y="954" width="279" height="447"/>
	<SubTexture name="slugcatright0004" x="931" y="954" width="279" height="447"/>
	<SubTexture name="slugcatright0005" x="931" y="954" width="279" height="447"/>
	<SubTexture name="slugcatright0006" x="931" y="954" width="279" height="447"/>
	<SubTexture name="slugcatright0007" x="931" y="954" width="279" height="447"/>
	<SubTexture name="slugcatright0008" x="931" y="954" width="279" height="447"/>
	<SubTexture name="slugcatright0009" x="931" y="954" width="279" height="447"/>
	<SubTexture name="slugcatright0010" x="931" y="954" width="279" height="447"/>
	<SubTexture name="slugcatright0011" x="931" y="954" width="279" height="447"/>
	<SubTexture name="slugcatright0012" x="931" y="954" width="279" height="447"/>
	<SubTexture name="slugcatright0013" x="931" y="954" width="279" height="447"/>
	<SubTexture name="slugcatright0014" x="931" y="954" width="279" height="447"/>
	<SubTexture name="slugcatup0000" x="1226" y="954" width="383" height="428"/>
	<SubTexture name="slugcatup0001" x="1226" y="954" width="383" height="428"/>
	<SubTexture name="slugcatup0002" x="1625" y="954" width="383" height="428"/>
	<SubTexture name="slugcatup0003" x="1625" y="954" width="383" height="428"/>
	<SubTexture name="slugcatup0004" x="16" y="1430" width="383" height="428"/>
	<SubTexture name="slugcatup0005" x="16" y="1430" width="383" height="428"/>
	<SubTexture name="slugcatup0006" x="16" y="1430" width="383" height="428"/>
	<SubTexture name="slugcatup0007" x="16" y="1430" width="383" height="428"/>
	<SubTexture name="slugcatup0008" x="16" y="1430" width="383" height="428"/>
	<SubTexture name="slugcatup0009" x="16" y="1430" width="383" height="428"/>
	<SubTexture name="slugcatup0010" x="16" y="1430" width="383" height="428"/>
	<SubTexture name="slugcatup0011" x="16" y="1430" width="383" height="428"/>
	<SubTexture name="slugcatup0012" x="16" y="1430" width="383" height="428"/>
	<SubTexture name="slugcatup0013" x="16" y="1430" width="383" height="428"/>
	<SubTexture name="slugcatup0014" x="16" y="1430" width="383" height="428"/>
</TextureAtlas>
